{
  "owner": "reviewdog",
  "repo": "action-flake8",
  "repos": [
    {
      "url": "https://github.com/netdata/netdata",
      "stars": 76278
    },
    {
      "url": "https://github.com/bndr/pipreqs",
      "stars": 7343
    },
    {
      "url": "https://github.com/BaguaSys/bagua",
      "stars": 881
    },
    {
      "url": "https://github.com/tradingstrategy-ai/web3-ethereum-defi",
      "stars": 735
    },
    {
      "url": "https://github.com/simpeg/simpeg",
      "stars": 585
    },
    {
      "url": "https://github.com/lavenderdotpet/LibreQuake",
      "stars": 573
    },
    {
      "url": "https://github.com/pnuckowski/aioresponses",
      "stars": 550
    },
    {
      "url": "https://github.com/PersiaML/PERSIA",
      "stars": 409
    },
    {
      "url": "https://github.com/PAhelper/PhoenixAdult.bundle",
      "stars": 377
    },
    {
      "url": "https://github.com/f0uriest/interpax",
      "stars": 224
    },
    {
      "url": "https://github.com/ThePornDatabase/ThePornDB.bundle",
      "stars": 222
    },
    {
      "url": "https://github.com/libcgroup/libcgroup",
      "stars": 168
    },
    {
      "url": "https://github.com/PlasmaControl/DESC",
      "stars": 139
    },
    {
      "url": "https://github.com/mangdangroboticsclub/mini_pupper_ros",
      "stars": 124
    },
    {
      "url": "https://github.com/ehpor/hcipy",
      "stars": 122
    },
    {
      "url": "https://github.com/fdintino/pillow-avif-plugin",
      "stars": 112
    },
    {
      "url": "https://github.com/LFPy/LFPy",
      "stars": 83
    },
    {
      "url": "https://github.com/ydb-platform/nbs",
      "stars": 80
    },
    {
      "url": "https://github.com/ccdc-opensource/csd-python-api-scripts",
      "stars": 80
    },
    {
      "url": "https://github.com/ktsaou/netdata",
      "stars": 79
    },
    {
      "url": "https://github.com/f0uriest/quadax",
      "stars": 70
    },
    {
      "url": "https://github.com/oracle/adaptivemm",
      "stars": 67
    },
    {
      "url": "https://github.com/ThePornDatabase/scrapers",
      "stars": 66
    },
    {
      "url": "https://github.com/ut-issl/c2a-core",
      "stars": 55
    },
    {
      "url": "https://github.com/michaelthomasletts/boto3-refresh-session",
      "stars": 47
    },
    {
      "url": "https://github.com/rickstaa/ros-gazebo-gym",
      "stars": 45
    },
    {
      "url": "https://github.com/Open-Model-Initiative/OMI-Data-Pipeline",
      "stars": 35
    },
    {
      "url": "https://github.com/NebularNerd/subtotxt",
      "stars": 30
    },
    {
      "url": "https://github.com/comorment/containers",
      "stars": 30
    },
    {
      "url": "https://github.com/ZPascal/grafana_api_sdk",
      "stars": 29
    },
    {
      "url": "https://github.com/f0uriest/orthax",
      "stars": 25
    },
    {
      "url": "https://github.com/DirtyRacer1337/PhoenixAdult.bundle",
      "stars": 23
    },
    {
      "url": "https://github.com/arkedge/c2a-core",
      "stars": 21
    },
    {
      "url": "https://github.com/ccdc-opensource/ansible-role-debloat-windows",
      "stars": 19
    },
    {
      "url": "https://github.com/danishi/dynamodb-csv",
      "stars": 19
    },
    {
      "url": "https://github.com/nnsnodnb/django-ios-storekit",
      "stars": 19
    },
    {
      "url": "https://github.com/rickstaa/panda-gazebo",
      "stars": 18
    },
    {
      "url": "https://github.com/mikhailprivalov/l2",
      "stars": 18
    },
    {
      "url": "https://github.com/nnsnodnb/kalyke",
      "stars": 18
    },
    {
      "url": "https://github.com/istellartech/GELATO",
      "stars": 16
    },
    {
      "url": "https://github.com/ccdc-opensource/dash",
      "stars": 12
    },
    {
      "url": "https://github.com/rickstaa/stable-gym",
      "stars": 11
    },
    {
      "url": "https://github.com/ccdc-opensource/science-paper-rf-machine-learned-scoring-2022",
      "stars": 10
    },
    {
      "url": "https://github.com/stackabletech/spark-operator",
      "stars": 9
    },
    {
      "url": "https://github.com/BedrockStreaming/hsdo",
      "stars": 7
    },
    {
      "url": "https://github.com/Police-Data-Accessibility-Project/data-source-manager",
      "stars": 6
    },
    {
      "url": "https://github.com/rickstaa/stable-learning-control",
      "stars": 6
    },
    {
      "url": "https://github.com/stackabletech/druid-opa-authorizer",
      "stars": 6
    },
    {
      "url": "https://github.com/LFPy/LFPykernels",
      "stars": 6
    },
    {
      "url": "https://github.com/idiv-biodiversity/scddl",
      "stars": 5
    },
    {
      "url": "https://github.com/rickstaa/ros-gazebo-gym-examples",
      "stars": 5
    },
    {
      "url": "https://github.com/NurOrNuLL/ESDP-AP-5-6-TEAM-2",
      "stars": 5
    }
  ],
  "count": {
    "total": 538,
    "public": 321,
    "private": 217,
    "more_than_zero_star": 120
  }
}
